mlfompy/__init__.py
mlfompy/auxiliar.py
mlfompy/extraction_methods.py
mlfompy/ml_models.py
mlfompy/ml_train_exp.py
mlfompy/mlfompy_dataset.py
mlfompy/output_files.py
mlfompy/parser.py
mlfompy/plots.py
mlfompy-0.0.4.dist-info/LICENSE.rst
mlfompy-0.0.4.dist-info/METADATA
mlfompy-0.0.4.dist-info/WHEEL
mlfompy-0.0.4.dist-info/top_level.txt
mlfompy-0.0.4.dist-info/RECORD
