Metadata-Version: 2.1
Name: mlfompy
Version: 0.0.4
Summary: MLFoMPy is an effective tool that extracts the main figures of merit (FoM) of a semiconductors IV curve
Home-page: https://gitlab.citius.usc.es/modev/mlfompy
Author: 
Author-email: 
Classifier: Topic :: Utilities
Classifier: Intended Audience :: Developers
Classifier: Intended Audience :: Information Technology
Classifier: License :: OSI Approved :: GNU General Public License v3 (GPLv3)
Classifier: Operating System :: Unix
Classifier: Programming Language :: Python :: 3
Requires-Python: >=3.6
License-File: LICENSE.rst
Requires-Dist: pytest
Requires-Dist: scipy
Requires-Dist: matplotlib
Requires-Dist: numpy
Requires-Dist: pyocclient
Requires-Dist: yachalk
Requires-Dist: seaborn
Provides-Extra: ml
Requires-Dist: torch ; extra == 'ml'
Requires-Dist: pytorch-lightning ; extra == 'ml'
Requires-Dist: torcheval ; extra == 'ml'
Requires-Dist: torchmetrics ; extra == 'ml'
Requires-Dist: scikit-learn ; extra == 'ml'
